wumpy/bot/__init__.py
wumpy/bot/_bot.py
wumpy/bot/_dispatch.py
wumpy/bot/_errors.py
wumpy/bot/_extension.py
wumpy/bot/_utils.py
wumpy/bot/py.typed
wumpy/bot/events/__init__.py
wumpy/bot/events/_channel.py
wumpy/bot/events/_gateway.py
wumpy/bot/events/_guild.py
wumpy/bot/events/_message.py
wumpy_bot-0.1.0.dist-info/WHEEL
wumpy_bot-0.1.0.dist-info/METADATA
wumpy_bot-0.1.0.dist-info/RECORD
